Spruce_pkg-0.1.3-py2.7-nspkg.pth
spruce/pkg/_envs.py
spruce/pkg/_projects_misc.py
spruce/pkg/_std.py
spruce/pkg/_projects.py
spruce/pkg/_exc.py
spruce/pkg/_requirements.py
spruce/pkg/_dists_misc.py
spruce/pkg/_misc.py
spruce/pkg/_dists.py
spruce/pkg/__init__.py
spruce/pkg/scripts/find_pyprojects.py
spruce/pkg/scripts/__init__.py
Spruce_pkg-0.1.3.dist-info/top_level.txt
Spruce_pkg-0.1.3.dist-info/RECORD
Spruce_pkg-0.1.3.dist-info/pydist.json
Spruce_pkg-0.1.3.dist-info/WHEEL
Spruce_pkg-0.1.3.dist-info/namespace_packages.txt
Spruce_pkg-0.1.3.dist-info/METADATA
Spruce_pkg-0.1.3.dist-info/entry_points.txt
Spruce_pkg-0.1.3.dist-info/DESCRIPTION.rst
Spruce_pkg-0.1.3.data/scripts/sort-pyproject-deps
Spruce_pkg-0.1.3.data/scripts/find-pyprojects
Spruce_pkg-0.1.3.data/scripts/find-devel-pyprojects
Spruce_pkg-0.1.3.data/scripts/sort-devel-pyproject-deps
