Metadata-Version: 2.0
Name: Spruce-pkg
Version: 0.1.3
Summary: Packaging
Home-page: UNKNOWN
Author: Ivan D Vasin
Author-email: nisavid@gmail.com
License: GNU LESSER GENERAL PUBLIC LICENSE
